{
  "kind": "collectionType",
  "collectionName": "promotions",
  "info": {
    "singularName": "promotion",
    "pluralName": "promotions",
    "displayName": "Promotion"
  },
  "options": {
    "draftAndPublish": true
  },
  "pluginOptions": {
    "i18n": {
      "localized": false
    }
  },
  "attributes": {
    "titre": {
      "type": "string",
      "required": true
    },
    "lien_de_redirection": {
      "type": "string"
    },
    "image": {
      "type": "media",
      "multiple": false,
      "required": true,
      "allowedTypes": [
        "images"
      ]
    }
  }
}
